{
  "project_name": "coveragepy",
  "code_dirs": {
    "coverage": {
      "py": 39,
      "ipynb": 0,
      "total": 39
    },
    "lab": {
      "py": 18,
      "ipynb": 0,
      "total": 18
    },
    "ci": {
      "py": 4,
      "ipynb": 0,
      "total": 4
    },
    "doc": {
      "py": 2,
      "ipynb": 0,
      "total": 2
    }
  },
  "deps_file": [
    {
      "source_type": "DepsSource",
      "path": "pyproject.toml",
      "parser_choice": "pyproject.toml",
      "deps_count": 0,
      "warnings": false
    },
    {
      "source_type": "DepsSource",
      "path": "setup.py",
      "parser_choice": "setup.py",
      "deps_count": 0,
      "warnings": true
    },
    {
      "source_type": "DepsSource",
      "path": "doc/requirements.in",
      "parser_choice": "requirements.txt",
      "deps_count": 7,
      "warnings": false
    }
  ],
  "imports": [
    {
      "Conditional imports": {
        "name": "third",
        "source": {
          "path": "tests/plugin2.py",
          "lineno": 17
        }
      }
    },
    {
      "Conditional imports": {
        "name": "_structseq",
        "source": {
          "path": "coverage/inorout.py",
          "lineno": 46
        }
      }
    },
    {
      "Conditional imports": {
        "name": "_pypy_irc_topic",
        "source": {
          "path": "coverage/inorout.py",
          "lineno": 52
        }
      }
    }
  ],
  "fawltydeps_version": "0.13.1"
}