{
  "project_name": "gseapy",
  "code_dirs": {
    "gseapy": {
      "py": 15,
      "ipynb": 0,
      "total": 15
    },
    "docs": {
      "py": 1,
      "ipynb": 2,
      "total": 3
    }
  },
  "deps_file": [
    {
      "source_type": "DepsSource",
      "path": "test-requirements.txt",
      "parser_choice": "requirements.txt",
      "deps_count": 6,
      "warnings": false
    },
    {
      "source_type": "DepsSource",
      "path": "setup.py",
      "parser_choice": "setup.py",
      "deps_count": 5,
      "warnings": true
    },
    {
      "source_type": "DepsSource",
      "path": "pyproject.toml",
      "parser_choice": "pyproject.toml",
      "deps_count": 0,
      "warnings": false
    },
    {
      "source_type": "DepsSource",
      "path": "docs/docs-requirements.txt",
      "parser_choice": "requirements.txt",
      "deps_count": 18,
      "warnings": false
    },
    {
      "source_type": "DepsSource",
      "path": "requirements.txt",
      "parser_choice": "requirements.txt",
      "deps_count": 8,
      "warnings": false
    }
  ],
  "imports": [],
  "fawltydeps_version": "0.13.1"
}