{
  "project_name": "openprescribing",
  "code_dirs": {
    "openprescribing": {
      "py": 304,
      "ipynb": 0,
      "total": 304
    },
    "deploy": {
      "py": 2,
      "ipynb": 0,
      "total": 2
    },
    "scripts": {
      "py": 2,
      "ipynb": 0,
      "total": 2
    },
    "notebooks": {
      "py": 0,
      "ipynb": 1,
      "total": 1
    }
  },
  "deps_file": [
    {
      "source_type": "DepsSource",
      "path": "requirements.in",
      "parser_choice": "requirements.txt",
      "deps_count": 53,
      "warnings": false
    },
    {
      "source_type": "DepsSource",
      "path": "requirements.dev.txt",
      "parser_choice": "requirements.txt",
      "deps_count": 18,
      "warnings": false
    },
    {
      "source_type": "DepsSource",
      "path": "setup.cfg",
      "parser_choice": "setup.cfg",
      "deps_count": 0,
      "warnings": false
    },
    {
      "source_type": "DepsSource",
      "path": "requirements.dev.in",
      "parser_choice": "requirements.txt",
      "deps_count": 3,
      "warnings": false
    },
    {
      "source_type": "DepsSource",
      "path": "pyproject.toml",
      "parser_choice": "pyproject.toml",
      "deps_count": 0,
      "warnings": false
    },
    {
      "source_type": "DepsSource",
      "path": "requirements.txt",
      "parser_choice": "requirements.txt",
      "deps_count": 117,
      "warnings": false
    }
  ],
  "imports": [],
  "fawltydeps_version": "0.13.1"
}