{
  "project_name": "sim_and_scat",
  "code_dirs": {
    "content": {
      "py": 2,
      "ipynb": 18,
      "total": 20
    },
    "run_local": {
      "py": 0,
      "ipynb": 18,
      "total": 18
    },
    "scripts": {
      "py": 6,
      "ipynb": 1,
      "total": 7
    },
    "_build": {
      "py": 2,
      "ipynb": 0,
      "total": 2
    }
  },
  "deps_file": [
    {
      "source_type": "DepsSource",
      "path": "build-requirements.txt",
      "parser_choice": "requirements.txt",
      "deps_count": 5,
      "warnings": false
    },
    {
      "source_type": "DepsSource",
      "path": "requirements.txt",
      "parser_choice": "requirements.txt",
      "deps_count": 8,
      "warnings": false
    }
  ],
  "imports": [],
  "fawltydeps_version": "0.13.1"
}