{
  "project_name": "uap",
  "code_dirs": {
    "include": {
      "py": 129,
      "ipynb": 0,
      "total": 129
    },
    "tools": {
      "py": 20,
      "ipynb": 0,
      "total": 20
    },
    "doc": {
      "py": 3,
      "ipynb": 0,
      "total": 3
    }
  },
  "deps_file": [
    {
      "source_type": "DepsSource",
      "path": "example-configurations/travis-example/requirements.txt",
      "parser_choice": "requirements.txt",
      "deps_count": 1,
      "warnings": false
    },
    {
      "source_type": "DepsSource",
      "path": "doc/requirements.txt",
      "parser_choice": "requirements.txt",
      "deps_count": 2,
      "warnings": false
    },
    {
      "source_type": "DepsSource",
      "path": "setup.py",
      "parser_choice": "setup.py",
      "deps_count": 4,
      "warnings": true
    }
  ],
  "imports": [],
  "fawltydeps_version": "0.13.1"
}